{
    "schema_version": "v1",
    "name_for_human": "Local: Owen Flights Plugin",
    "name_for_model": "owenFlightsPlugin",
    "description_for_human": "Local: Plugin for flights search using Skyscanner.net",
    "description_for_model": "Plugin for searching for flights deals using the skyscanner apis",
    "auth": {
        "type": "none"
    },
    "api": {
        "type": "openapi",
        "url": "https://api.flights.owenmerry.com/open-api.yaml",
        "is_user_authenticated": false
    },
    "logo_url": "https://api.flights.owenmerry.com/owen-logo.png",
    "contact_email": "me@owenmerry.com",
    "legal_info_url": "http://www.owenmerry.com"
}